<?xml version="1.0" encoding="utf-8"?>
<publishData>
  <publishProfile publishUrl="C:\inetpub\wwwroot\moneypacific" deleteExistingFiles="True" ftpAnonymousLogin="False" ftpPassiveMode="True" msdeploySite="" msdeploySiteID="" msdeployRemoteSitePhysicalPath="" msdeployAllowUntrustedCertificate="False" msdeploySkipExtraFilesOnServer="True" msdeployMarkAsApp="False" profileName="Profile1" publishMethod="FileSystem" replaceMatchingFiles="False" userName="" savePWD="False" userPWD="" SelectedForPublish="True">
    <file relUrl="bin/GeneratorPacificCode.dll" publishTime="11/22/2010 14:15:44" />
    <file relUrl="bin/MoneyPacificSrv.pdb" publishTime="11/23/2010 17:12:45" />
    <file relUrl="XAO/PacificCodeXAO.cs.txt" publishTime="10/14/2010 18:54:28" />
    <file relUrl="App_Data/Language.xml" publishTime="10/01/2010 16:44:09" />
    <file relUrl="bin/MoneyPacificSrv.dll" publishTime="11/23/2010 17:12:46" />
    <file relUrl="Web.config" publishTime="11/18/2010 14:22:49" />
    <file relUrl="Main.svc" publishTime="09/27/2010 10:40:35" />
    <file relUrl="App_Data/PacificCodeR.xml" publishTime="10/01/2010 11:14:48" />
    <file relUrl="bin/GeneratorPacificCode.pdb" publishTime="11/22/2010 14:15:44" />
  </publishProfile>
</publishData>